CHANGELOG
LICENSE
MANIFEST.in
README
setup.py
spotimeta/__init__.py
spotimeta/parser.py
spotimeta.egg-info/PKG-INFO
spotimeta.egg-info/SOURCES.txt
spotimeta.egg-info/dependency_links.txt
spotimeta.egg-info/entry_points.txt
spotimeta.egg-info/not-zip-safe
spotimeta.egg-info/top_level.txt