Metadata-Version: 1.0
Name: spotimeta
Version: 0.1
Summary: "Library for querying the Spotify metadata service
Home-page: http://bitbucket.org/runeh/spotimeta/
Author: Rune Halvorsen
Author-email: runefh@gmail.com
License: BSD
Keywords: Spotify
Platform: UNKNOWN
Classifier: Programming Language :: Python
Classifier: Intended Audience :: Developers
Classifier: License :: OSI Approved :: BSD License
